pos_printer/__init__.py
pos_printer/_version.py
pos_printer/main.py
inbox4us_pos_printer-0.1.4.dist-info/METADATA
inbox4us_pos_printer-0.1.4.dist-info/WHEEL
inbox4us_pos_printer-0.1.4.dist-info/top_level.txt
inbox4us_pos_printer-0.1.4.dist-info/RECORD
